pycitysim/__init__.py
pycitysim/apphub/__init__.py
pycitysim/apphub/apphub.py
pycitysim/map/__init__.py
pycitysim/map/map.py
pycitysim/routing/__init__.py
pycitysim/routing/client.py
pycitysim/sateimg/__init__.py
pycitysim/sateimg/_utils.py
pycitysim/sateimg/sateimg.py
pycitysim/sidecar/__init__.py
pycitysim/sidecar/sidecar.py
pycitysim/sidecar/sidecarv2.py
pycitysim/sim/__init__.py
pycitysim/sim/aoi_service.py
pycitysim/sim/client.py
pycitysim/sim/clock_service.py
pycitysim/sim/economy_services.py
pycitysim/sim/lane_service.py
pycitysim/sim/light_service.py
pycitysim/sim/person_service.py
pycitysim/sim/road_service.py
pycitysim/sim/social_service.py
pycitysim/streetview/__init__.py
pycitysim/streetview/baidu.py
pycitysim/streetview/equirectangular.py
pycitysim/streetview/google.py
pycitysim/urbankg/__init__.py
pycitysim/urbankg/kg.py
pycitysim/utils/__init__.py
pycitysim/utils/geojson.py
pycitysim/utils/grpc.py
pycitysim/utils/protobuf.py
pycitysim-1.21.0.dist-info/LICENSE
pycitysim-1.21.0.dist-info/METADATA
pycitysim-1.21.0.dist-info/WHEEL
pycitysim-1.21.0.dist-info/top_level.txt
pycitysim-1.21.0.dist-info/RECORD
