Metadata-Version: 2.1
Name: pycitysim
Version: 1.21.0
Summary: City Simulator and OpenCity Databases Python SDK
Author-email: Jun Zhang <zhangjun990222@gmail.com>
License: MIT License
Project-URL: Homepage, https://github.com/tsinghua-fib-lab/pycitysim
Project-URL: Documentation, https://pycitysim.sim.fiblab.net/pycitysim
Project-URL: Repository, https://github.com/tsinghua-fib-lab/pycitysim.git
Project-URL: Issues, https://github.com/tsinghua-fib-lab/pycitysim/issues
Keywords: city,simulation,database,sdk
Classifier: Programming Language :: Python :: 3
Classifier: Operating System :: OS Independent
Requires-Python: >=3.8
License-File: LICENSE
Requires-Dist: Deprecated >=1.2.0
Requires-Dist: geojson >=3.1.0
Requires-Dist: geopandas >=0.9.0
Requires-Dist: grpcio <2.0.0,>=1.42.0
Requires-Dist: lru-dict >=1.3.0
Requires-Dist: numpy >=1.24.0
Requires-Dist: opencv-python >=4.8.0.74
Requires-Dist: Pillow >=10.0.0
Requires-Dist: pycityproto ==1.20.0
Requires-Dist: pymongo >=3.12.1
Requires-Dist: pyproj >=3.0.0
Requires-Dist: requests >=2.27.0
Requires-Dist: scipy >=1.7.0
Requires-Dist: shapely >=2.0.0
Requires-Dist: stringcase >=1.2.0
Requires-Dist: importlib-metadata ; python_version < "3.8"
